Tbqc/Tbqc.py
Tbqc/__init__.py
Tbqc-0.0.3.dist-info/LICENSE
Tbqc-0.0.3.dist-info/METADATA
Tbqc-0.0.3.dist-info/WHEEL
Tbqc-0.0.3.dist-info/top_level.txt
Tbqc-0.0.3.dist-info/RECORD
