Metadata-Version: 2.1
Name: Tbqc
Version: 0.0.3
Summary: Taiwan Bartender Quizdata Crawler
Home-page: https://github.com/dapingtai/Tw-Bartender-Quizdata-crawler/
Author: HungChang
Author-email: zero100x@gmail.com
License: BSD-5
Platform: UNKNOWN
Requires-Python: >=3.6
